{"name":"test001","id":"com.restapiexample.userinfo.EmployeeCURDTest:test001","testCaseName":"com.restapiexample.userinfo.EmployeeCURDTest","userStory":{"id":"com.restapiexample.userinfo.EmployeeCURDTest","storyName":"Employee CURD test","storyClassName":"com.restapiexample.userinfo.EmployeeCURDTest","path":"com.restapiexample.userinfo","type":"story"},"featureTag":{"name":"Userinfo/Employee CURD test","type":"story"},"title":"This will create a new employee","tags":[{"name":"Userinfo/Employee CURD test","type":"story"}],"startTime":"2022-06-07T15:18:47.607+01:00[Europe/London]","duration":216,"testFailureCause":{"errorType":"java.lang.IllegalArgumentException","message":"baseURI cannot be null","stackTrace":[{"declaringClass":"io.restassured.internal.assertion.AssertParameter","methodName":"notNull","fileName":"AssertParameter.groovy","lineNumber":26},{"declaringClass":"io.restassured.internal.RequestSpecificationImpl","methodName":"\u003cinit\u003e","fileName":"RequestSpecificationImpl.groovy","lineNumber":132},{"declaringClass":"io.restassured.RestAssured","methodName":"createTestSpecification","fileName":"RestAssured.java","lineNumber":1492},{"declaringClass":"io.restassured.RestAssured","methodName":"given","fileName":"RestAssured.java","lineNumber":711},{"declaringClass":"net.serenitybdd.rest.SerenityRest","methodName":"given","fileName":"SerenityRest.java","lineNumber":211},{"declaringClass":"com.restapiexample.userinfo.EmployeeCURDTest","methodName":"test001","fileName":"EmployeeCURDTest.java","lineNumber":35}]},"testFailureClassname":"java.lang.IllegalArgumentException","testFailureMessage":"baseURI cannot be null","testFailureSummary":"ERROR;java.lang.IllegalArgumentException;baseURI cannot be null;AssertParameter.groovy","projectKey":"","annotatedResult":"ERROR","manual":false,"testSource":"JUnit","result":"ERROR"}